checkpoint_schedules/__init__.py
checkpoint_schedules/basic_schedules.py
checkpoint_schedules/hrevolve.py
checkpoint_schedules/mixed.py
checkpoint_schedules/multistage.py
checkpoint_schedules/schedule.py
checkpoint_schedules/twolevel_binomial.py
checkpoint_schedules/hrevolve_sequences/__init__.py
checkpoint_schedules/hrevolve_sequences/basic_functions.py
checkpoint_schedules/hrevolve_sequences/disk_revolve.py
checkpoint_schedules/hrevolve_sequences/hrevolve.py
checkpoint_schedules/hrevolve_sequences/periodic_disk_revolve.py
checkpoint_schedules/hrevolve_sequences/revolve.py
checkpoint_schedules/hrevolve_sequences/revolve_1d.py
checkpoint_schedules/hrevolve_sequences/utils.py
checkpoint_schedules-1.0.4.dist-info/LICENSE
checkpoint_schedules-1.0.4.dist-info/METADATA
checkpoint_schedules-1.0.4.dist-info/WHEEL
checkpoint_schedules-1.0.4.dist-info/top_level.txt
checkpoint_schedules-1.0.4.dist-info/RECORD
